climkern/__init__.py
climkern/__main__.py
climkern/download.py
climkern/frontend.py
climkern/util.py
climkern/tests/conftest.py
climkern/tests/test_frontend.py
climkern-1.2.dist-info/LICENSE
climkern-1.2.dist-info/METADATA
climkern-1.2.dist-info/WHEEL
climkern-1.2.dist-info/top_level.txt
climkern-1.2.dist-info/RECORD
