Metadata-Version: 2.2
Name: climkern
Version: 1.2
Author-email: Ty Janoski <tyfolino@gmail.com>
Requires-Python: >=3.9
License-File: LICENSE
Requires-Dist: xarray>=0.16.2
Requires-Dist: cf-xarray>=0.5.1
Requires-Dist: cftime
Requires-Dist: xesmf>=0.7.1
Requires-Dist: importlib_resources
Requires-Dist: pooch
Requires-Dist: tqdm
Requires-Dist: plac
Requires-Dist: netCDF4
Provides-Extra: test
Requires-Dist: pytest<8,>=7; extra == "test"
Provides-Extra: lint
Requires-Dist: precommit>=2.20.0; extra == "lint"
